img/paper.gif
paper_animator/__init__.py
paper_animator/__main__.py
paper_animator/animate.py
paper_animator/extract.py
paper_animator-0.0.2.dist-info/entry_points.txt
paper_animator-0.0.2.dist-info/WHEEL
paper_animator-0.0.2.dist-info/METADATA
paper_animator-0.0.2.dist-info/RECORD
