Metadata-Version: 2.1
Name: paper-animator
Version: 0.0.2
Summary: Animate a version-controlled PDF/LaTeX paper!
Home-page: https://github.com/sneakers-the-rat/paper-animator
License: MPL-2.0
Author: sneakers-the-rat
Author-email: JLSaunders987@gmail.com
Requires-Python: >=3.8,<4.0
Classifier: License :: OSI Approved
Classifier: Programming Language :: Python :: 3
Classifier: Programming Language :: Python :: 3.8
Requires-Dist: gitpython (>=3.1.13,<4.0.0)
Requires-Dist: matplotlib (>=3.3.4,<4.0.0)
Requires-Dist: numpy (>=1.20.1,<2.0.0)
Requires-Dist: pymupdf (>=1.18.8,<2.0.0)
Requires-Dist: pypng (>=0.0.20,<0.0.21)
Requires-Dist: scikit-video (>=1.1.11,<2.0.0)
Requires-Dist: tqdm (>=4.57.0,<5.0.0)
Project-URL: Repository, https://github.com/sneakers-the-rat/paper-animator
